{
  "version": 2,
  "extractor": "papercropper",
  "figures": [
    {
      "url": "assets/figures/arxiv/2607.02396v1/fig-001.webp",
      "caption": "",
      "page": 0,
      "index": 1,
      "width": 834,
      "height": 490,
      "label": "Figure"
    },
    {
      "url": "assets/figures/arxiv/2607.02396v1/fig-002.webp",
      "caption": "",
      "page": 0,
      "index": 2,
      "width": 751,
      "height": 474,
      "label": "Figure"
    },
    {
      "url": "assets/figures/arxiv/2607.02396v1/fig-003.webp",
      "caption": "",
      "page": 0,
      "index": 3,
      "width": 749,
      "height": 472,
      "label": "Figure"
    },
    {
      "url": "assets/figures/arxiv/2607.02396v1/fig-004.webp",
      "caption": "",
      "page": 0,
      "index": 4,
      "width": 747,
      "height": 473,
      "label": "Figure"
    },
    {
      "url": "assets/figures/arxiv/2607.02396v1/fig-005.webp",
      "caption": "",
      "page": 0,
      "index": 5,
      "width": 832,
      "height": 501,
      "label": "Figure"
    },
    {
      "url": "assets/figures/arxiv/2607.02396v1/fig-006.webp",
      "caption": "",
      "page": 0,
      "index": 6,
      "width": 1709,
      "height": 999,
      "label": "Figure"
    }
  ]
}